setup.py
ppbank/extract_docx.py
ppbank/inter.py
ppbank/moleclues_info.py
ppbank/ppbank.py
ppbank/test.py
ppbank/transform.py
ppbank.egg-info/PKG-INFO
ppbank.egg-info/SOURCES.txt
ppbank.egg-info/dependency_links.txt
ppbank.egg-info/requires.txt
ppbank.egg-info/top_level.txt
resources/__init__.py