Metadata-Version: 1.1
Name: ppbank
Version: 2.1.7
Summary: PPbank Cli Tools
Home-page: https://docs.snquantum.com/ppbank
Author: lhr
Author-email: airhenry@gmail.com
License: UNKNOWN
Platform: UNKNOWN
Classifier: Development Status :: 4 - Beta
Classifier: Intended Audience :: Developers
Classifier: Environment :: Console
Classifier: License :: OSI Approved :: MIT License
Classifier: Programming Language :: Python :: 3.6
Classifier: Programming Language :: Python :: 3.7
Classifier: Programming Language :: Python :: 3.8
Classifier: Programming Language :: Python :: 3.9
